biasondemand/__init__.py
biasondemand/generate_dataset.py
biasondemand-0.1.0.dist-info/LICENSE
biasondemand-0.1.0.dist-info/METADATA
biasondemand-0.1.0.dist-info/WHEEL
biasondemand-0.1.0.dist-info/entry_points.txt
biasondemand-0.1.0.dist-info/top_level.txt
biasondemand-0.1.0.dist-info/RECORD
