Metadata-Version: 2.1
Name: biasondemand
Version: 0.1.0
Summary: A Python package that generates synthetic datasets with different types of bias
Author-email: Joachim Baumann <joachimbaumann1@gmail.com>, Alessandro Castelnovo <alessandro.castelnovo@intesasanpaolo.com>, Riccardo Crupi <riccardo.crupi@intesasanpaolo.com>, Nicole Inverardi <nicole.inverardi@intesasanpaolo.com>, Daniele Regoli <daniele.regoli@intesasanpaolo.com>
License: MIT
Project-URL: Homepage, https://github.com/joebaumann/biasondemand
Keywords: bias,dataset,synthetic data
Classifier: Development Status :: 3 - Alpha
Classifier: Intended Audience :: Science/Research
Classifier: License :: OSI Approved :: MIT License
Classifier: Programming Language :: Python :: 3
Classifier: Programming Language :: Python :: 3.8
Classifier: Programming Language :: Python :: 3.9
Requires-Python: >=3.7
License-File: LICENSE
Requires-Dist: numpy
Requires-Dist: pandas
Requires-Dist: scikit-learn
